noiserandom/__init__.py
noiserandom/main.py
noiserandom-2.1.dist-info/LICENSE
noiserandom-2.1.dist-info/METADATA
noiserandom-2.1.dist-info/WHEEL
noiserandom-2.1.dist-info/top_level.txt
noiserandom-2.1.dist-info/RECORD
