Metadata-Version: 2.1
Name: noiserandom
Version: 2.1
Home-page: https://github.com/AndreasKarageorgos/noiserandom
Author: Andreas Karageorgos
License: MIT
License-File: LICENSE
Requires-Dist: gmpy2
Requires-Dist: opencv-python
Requires-Dist: pycryptodome
